{
  "document_metadata": {
    "category": "Student ID"
  },
  "image_filename": "student_id_070.png",
  "image_dimensions": [
    640,
    640
  ],
  "words": [
    {
      "text": "E",
      "box": [
        317,
        448,
        373,
        570
      ],
      "label": "O"
    },
    {
      "text": "3",
      "box": [
        349,
        0,
        441,
        162
      ],
      "label": "O"
    },
    {
      "text": "1",
      "box": [
        513,
        6,
        555,
        148
      ],
      "label": "O"
    },
    {
      "text": "I",
      "box": [
        628,
        25,
        668,
        132
      ],
      "label": "O"
    },
    {
      "text": "1",
      "box": [
        743,
        42,
        778,
        124
      ],
      "label": "O"
    },
    {
      "text": "1",
      "box": [
        736,
        118,
        766,
        192
      ],
      "label": "O"
    },
    {
      "text": "1",
      "box": [
        614,
        123,
        656,
        217
      ],
      "label": "O"
    },
    {
      "text": "8",
      "box": [
        348,
        151,
        418,
        293
      ],
      "label": "O"
    },
    {
      "text": "0",
      "box": [
        728,
        189,
        761,
        256
      ],
      "label": "O"
    },
    {
      "text": "2",
      "box": [
        329,
        301,
        402,
        449
      ],
      "label": "O"
    },
    {
      "text": "I",
      "box": [
        280,
        564,
        370,
        865
      ],
      "label": "O"
    }
  ]
}